pyfmmlib/__init__.py
pyfmmlib/version.py
pyfmmlib/_internal.cpython-37m-x86_64-linux-gnu.so
pyfmmlib/.libs/libgomp-3300acd3.so.1.0.0
pyfmmlib/.libs/libgfortran-ed201abd.so.3.0.0
pyfmmlib-2019.1.5.dist-info/WHEEL
pyfmmlib-2019.1.5.dist-info/top_level.txt
pyfmmlib-2019.1.5.dist-info/METADATA
pyfmmlib-2019.1.5.dist-info/RECORD
