Metadata-Version: 1.1
Name: pyfmmlib
Version: 2019.1.5
Summary: Python wrappers for particle FMMs
Home-page: http://github.com/inducer/pyfmmlib
Author: Leslie Greengard, Zydrunas Gimbutas, Andreas Kloeckner
Author-email: inform@tiker.net
License: wrapper: MIT/code: 3-clause BSD
Platform: UNKNOWN
Classifier: Development Status :: 4 - Beta
Classifier: Intended Audience :: Developers
Classifier: Intended Audience :: Other Audience
Classifier: Intended Audience :: Science/Research
Classifier: License :: OSI Approved :: MIT License
Classifier: License :: OSI Approved :: BSD License
Classifier: Programming Language :: Fortran
Classifier: Programming Language :: Python
Classifier: Topic :: Scientific/Engineering
Classifier: Topic :: Scientific/Engineering :: Mathematics
Classifier: Topic :: Software Development :: Libraries
